LICENSE.txt
MANIFEST.in
README.rst
setup.cfg
setup.py
admin_csv/__init__.py
admin_csv/admin.py
admin_csv/templates/admin/change_list_csv.html
django_admin_csv.egg-info/PKG-INFO
django_admin_csv.egg-info/SOURCES.txt
django_admin_csv.egg-info/dependency_links.txt
django_admin_csv.egg-info/top_level.txt